GHAReports/GHAReports.py
GHAReports/__init__.py
GHAReports/__main__.py
GHAReports/cli.py
GHAReports/mdgen.py
robotframework_ghareports-0.9.1.dist-info/METADATA
robotframework_ghareports-0.9.1.dist-info/WHEEL
robotframework_ghareports-0.9.1.dist-info/entry_points.txt
robotframework_ghareports-0.9.1.dist-info/licenses/LICENSE
robotframework_ghareports-0.9.1.dist-info/RECORD
