Metadata-Version: 2.1
Name: robotframework-ghareports
Version: 0.9.1
Summary: Simple github action summary report for robotframework
Author-Email: Jani Mikkonen <jani.mikkonen@gmail.com>
License: GPLV3
Classifier: Development Status :: 4 - Beta
Classifier: Environment :: Console
Classifier: Intended Audience :: Developers
Classifier: Intended Audience :: End Users/Desktop
Classifier: Intended Audience :: Information Technology
Classifier: Intended Audience :: System Administrators
Classifier: Programming Language :: Python :: 3
Classifier: Programming Language :: Python :: 3.9
Classifier: Programming Language :: Python :: 3.10
Classifier: Programming Language :: Python :: 3.11
Classifier: Programming Language :: Python :: 3.12
Classifier: Programming Language :: Python :: 3.13
Classifier: Programming Language :: Python :: 3.14
Classifier: Topic :: Software Development :: Libraries
Classifier: Topic :: Software Development :: Quality Assurance
Classifier: Topic :: Software Development :: Testing
Classifier: Topic :: Utilities
Project-URL: Homepage, https://github.com/rasjani/robotframework-ghareports
Requires-Python: >=3.8
Requires-Dist: robotframework>=4.0.0
Requires-Dist: wrapt
Provides-Extra: dev
Requires-Dist: twine; extra == "dev"
Requires-Dist: python-language-server[all]; extra == "dev"
Requires-Dist: ruff; extra == "dev"
Requires-Dist: invoke; extra == "dev"
Requires-Dist: pdm; extra == "dev"
Requires-Dist: pytest; extra == "dev"
Requires-Dist: build; extra == "dev"
